{
  "4CzIPN": "C1=CC=C2C(=C1)C3=CC=CC=C3N2C4=C(C(=C(C(=C4C#N)N5C6=CC=CC=C6C7=CC=CC=C75)N8C9=CC=CC=C9C1=CC=CC=C18)N1C2=CC=CC=C2C2=CC=CC=C21)C#N",
  "CBP": "C1=CC=C2C(=C1)C=CC3=C2C=C4N3C5=CC=CC=C5C=N4",
  "DMAC-TRZ": "CN1CCOC2CN(CCC2C1)S(=O)(=O)C3=CC=C(C=C3)F.C(=O)(C(F)(F)F)O",
  "PXZ-TRZ": "CC1=CC=C(S1)CN2CCC3C2CCN3S(=O)(=O)C.C(=O)(C(F)(F)F)O",
  "DMAC-DPS": "CN1C=C(N=C1CCNC(=O)CC2=CC=CS2)C3=CC=CS3",
  "DMAC-BO": "CC(=CC(=O)C)O.CC(=CC(=O)C)O.CC(=CC(=O)C)O.O.[Sc]",
  "mACR-TRZ": "CN1CC2CN(CCC[C@@]2(C1)C(=O)O)C(=O)NCC3=CC(=CC=C3)F",
  "PXZ-BO": "CC(=O)N1CCOC2CN(CCC2C1)C(=O)NCC3=CN=CC=C3",
  "ACR-TRZ": "C1CCN(C1)C(=O)C2COCC3C2CN(C3)C4=NC=NC=C4.C(=O)(C(F)(F)F)O",
  "DMAC-BP": "CN(C)C1=NC2=CC=CC=C2C=C1c3ccc(cc3)C(=O)c4ccccc4",
  "DMAC-BN": "CN(C)C1=NC2=CC=CC=C2C=C1c3cccc(c3)C#N",
  "DPA-TRZ": "N(c1ccccc1)c2ccccc2c3nc(nc(n3)c4ccccc4)c5ccccc5"
}